<?xml version="1.0" standalone="yes" ?>
<!-- generated by lshw-B.02.18 -->
<!-- GCC 4.8.5 20150623 (Red Hat 4.8.5-44) -->
<!-- Linux 3.10.0-957.el7.x86_64 #1 SMP Thu Nov 8 23:39:32 UTC 2018 x86_64 -->
<!-- GNU libc 2 (glibc 2.17) -->
<list>
  <node id="sata:0" claimed="true" class="storage" handle="PCI:0000:00:11.5" modalias="pci:v00008086d0000A1D2sv00008086sd00007270bc01sc06i01">
   <description>SATA controller</description>
   <product>C620 Series Chipset Family SSATA Controller [AHCI mode]</product>
   <vendor>Intel Corporation</vendor>
   <physid>11.5</physid>
   <subsysproduct>Intel Corporation</subsysproduct>
   <subsysvendor>Intel Corporation</subsysvendor>
   <businfo>pci@0000:00:11.5</businfo>
   <version>08</version>
   <width units="bits">32</width>
   <clock units="Hz">66000000</clock>
   <configuration>
    <setting id="driver" value="ahci" />
    <setting id="latency" value="0" />
   </configuration>
   <capabilities>
    <capability id="sata" />
    <capability id="msi" >Message Signalled Interrupts</capability>
    <capability id="pm" >Power Management</capability>
    <capability id="ahci_1.0" />
    <capability id="bus_master" >bus mastering</capability>
    <capability id="cap_list" >PCI capabilities listing</capability>
   </capabilities>
   <resources>
    <resource type="irq" value="154" />
    <resource type="memory" value="9d206000-9d207fff" />
    <resource type="memory" value="9d209000-9d2090ff" />
    <resource type="ioport" value="3070(size=8)" />
    <resource type="ioport" value="3060(size=4)" />
    <resource type="ioport" value="3020(size=32)" />
    <resource type="memory" value="9d180000-9d1fffff" />
   </resources>
   <hints>
    <hint name="icon" value="disc" />
    <hint name="pci.class" value="0x106" />
    <hint name="pci.device" value="0xA1D2" />
    <hint name="pci.subdevice" value="0x7270" />
    <hint name="pci.subvendor" value="0x8086" />
    <hint name="pci.vendor" value="0x8086" />
   </hints>
  </node>
  <node id="sata:1" claimed="true" class="storage" handle="PCI:0000:00:17.0" modalias="pci:v00008086d0000A182sv00008086sd00007270bc01sc06i01">
   <description>SATA controller</description>
   <product>C620 Series Chipset Family SATA Controller [AHCI mode]</product>
   <vendor>Intel Corporation</vendor>
   <physid>17</physid>
   <subsysproduct>Intel Corporation</subsysproduct>
   <subsysvendor>Intel Corporation</subsysvendor>
   <businfo>pci@0000:00:17.0</businfo>
   <version>08</version>
   <width units="bits">32</width>
   <clock units="Hz">66000000</clock>
   <configuration>
    <setting id="driver" value="ahci" />
    <setting id="latency" value="0" />
   </configuration>
   <capabilities>
    <capability id="sata" />
    <capability id="msi" >Message Signalled Interrupts</capability>
    <capability id="pm" >Power Management</capability>
    <capability id="ahci_1.0" />
    <capability id="bus_master" >bus mastering</capability>
    <capability id="cap_list" >PCI capabilities listing</capability>
   </capabilities>
   <resources>
    <resource type="irq" value="163" />
    <resource type="memory" value="9d204000-9d205fff" />
    <resource type="memory" value="9d208000-9d2080ff" />
    <resource type="ioport" value="3050(size=8)" />
    <resource type="ioport" value="3040(size=4)" />
    <resource type="ioport" value="3000(size=32)" />
    <resource type="memory" value="9d100000-9d17ffff" />
   </resources>
   <hints>
    <hint name="icon" value="disc" />
    <hint name="pci.class" value="0x106" />
    <hint name="pci.device" value="0xA182" />
    <hint name="pci.subdevice" value="0x7270" />
    <hint name="pci.subvendor" value="0x8086" />
    <hint name="pci.vendor" value="0x8086" />
   </hints>
  </node>
  <node id="nvme" claimed="true" class="storage" handle="PCI:0000:18:00.0" modalias="pci:v00008086d00000953sv00008086sd00003703bc01sc08i02">
   <description>Non-Volatile memory controller</description>
   <product>PCIe Data Center SSD</product>
   <vendor>Intel Corporation</vendor>
   <physid>0</physid>
   <subsysproduct>Xeon C5500/C3500 DMI</subsysproduct>
   <subsysvendor>Intel Corporation</subsysvendor>
   <businfo>pci@0000:18:00.0</businfo>
   <version>01</version>
   <width units="bits">64</width>
   <clock units="Hz">33000000</clock>
   <configuration>
    <setting id="driver" value="nvme" />
    <setting id="latency" value="0" />
   </configuration>
   <capabilities>
    <capability id="nvme" />
    <capability id="pm" >Power Management</capability>
    <capability id="msix" >MSI-X</capability>
    <capability id="pciexpress" >PCI Express</capability>
    <capability id="nvm_express" />
    <capability id="bus_master" >bus mastering</capability>
    <capability id="cap_list" >PCI capabilities listing</capability>
    <capability id="rom" >extension ROM</capability>
   </capabilities>
   <resources>
    <resource type="irq" value="152" />
    <resource type="memory" value="a9010000-a9013fff" />
    <resource type="memory" value="a9000000-a900ffff" />
   </resources>
   <hints>
    <hint name="icon" value="disc" />
    <hint name="pci.class" value="0x108" />
    <hint name="pci.device" value="0x953" />
    <hint name="pci.subdevice" value="0x3703" />
    <hint name="pci.subvendor" value="0x8086" />
    <hint name="pci.vendor" value="0x8086" />
   </hints>
  </node>
  <node id="nvme" claimed="true" class="storage" handle="PCI:0000:1a:00.0" modalias="pci:v00001BB1d00000100sv00001BB1sd00000101bc01sc08i02">
   <description>Non-Volatile memory controller</description>
   <product>Nytro Flash Storage</product>
   <vendor>Seagate Technology PLC</vendor>
   <physid>0</physid>
   <subsysproduct>Seagate Technology PLC</subsysproduct>
   <subsysvendor>Seagate Technology PLC</subsysvendor>
   <businfo>pci@0000:1a:00.0</businfo>
   <version>00</version>
   <width units="bits">64</width>
   <clock units="Hz">33000000</clock>
   <configuration>
    <setting id="driver" value="nvme" />
    <setting id="latency" value="0" />
   </configuration>
   <capabilities>
    <capability id="nvme" />
    <capability id="pm" >Power Management</capability>
    <capability id="pciexpress" >PCI Express</capability>
    <capability id="msix" >MSI-X</capability>
    <capability id="nvm_express" />
    <capability id="bus_master" >bus mastering</capability>
    <capability id="cap_list" >PCI capabilities listing</capability>
    <capability id="rom" >extension ROM</capability>
   </capabilities>
   <resources>
    <resource type="irq" value="155" />
    <resource type="memory" value="a8010000-a8013fff" />
    <resource type="memory" value="a8000000-a800ffff" />
   </resources>
   <hints>
    <hint name="icon" value="disc" />
    <hint name="pci.class" value="0x108" />
    <hint name="pci.device" value="0x100" />
    <hint name="pci.subdevice" value="0x101" />
    <hint name="pci.subvendor" value="0x1BB1" />
    <hint name="pci.vendor" value="0x1BB1" />
   </hints>
  </node>
  <node id="nvme" claimed="true" class="storage" handle="PCI:0000:5e:00.0" modalias="pci:v00001BB1d00000100sv00001BB1sd00000101bc01sc08i02">
   <description>Non-Volatile memory controller</description>
   <product>Nytro Flash Storage</product>
   <vendor>Seagate Technology PLC</vendor>
   <physid>0</physid>
   <subsysproduct>Seagate Technology PLC</subsysproduct>
   <subsysvendor>Seagate Technology PLC</subsysvendor>
   <businfo>pci@0000:5e:00.0</businfo>
   <version>00</version>
   <width units="bits">64</width>
   <clock units="Hz">33000000</clock>
   <configuration>
    <setting id="driver" value="nvme" />
    <setting id="latency" value="0" />
   </configuration>
   <capabilities>
    <capability id="nvme" />
    <capability id="pm" >Power Management</capability>
    <capability id="pciexpress" >PCI Express</capability>
    <capability id="msix" >MSI-X</capability>
    <capability id="nvm_express" />
    <capability id="bus_master" >bus mastering</capability>
    <capability id="cap_list" >PCI capabilities listing</capability>
    <capability id="rom" >extension ROM</capability>
   </capabilities>
   <resources>
    <resource type="irq" value="157" />
    <resource type="memory" value="c4010000-c4013fff" />
    <resource type="memory" value="c4000000-c400ffff" />
   </resources>
   <hints>
    <hint name="icon" value="disc" />
    <hint name="pci.class" value="0x108" />
    <hint name="pci.device" value="0x100" />
    <hint name="pci.subdevice" value="0x101" />
    <hint name="pci.subvendor" value="0x1BB1" />
    <hint name="pci.vendor" value="0x1BB1" />
   </hints>
  </node>
  <node id="nvme" claimed="true" class="storage" handle="PCI:0000:60:00.0" modalias="pci:v00001BB1d00000100sv00001BB1sd00000101bc01sc08i02">
   <description>Non-Volatile memory controller</description>
   <product>Nytro Flash Storage</product>
   <vendor>Seagate Technology PLC</vendor>
   <physid>0</physid>
   <subsysproduct>Seagate Technology PLC</subsysproduct>
   <subsysvendor>Seagate Technology PLC</subsysvendor>
   <businfo>pci@0000:60:00.0</businfo>
   <version>00</version>
   <width units="bits">64</width>
   <clock units="Hz">33000000</clock>
   <configuration>
    <setting id="driver" value="nvme" />
    <setting id="latency" value="0" />
   </configuration>
   <capabilities>
    <capability id="nvme" />
    <capability id="pm" >Power Management</capability>
    <capability id="pciexpress" >PCI Express</capability>
    <capability id="msix" >MSI-X</capability>
    <capability id="nvm_express" />
    <capability id="bus_master" >bus mastering</capability>
    <capability id="cap_list" >PCI capabilities listing</capability>
    <capability id="rom" >extension ROM</capability>
   </capabilities>
   <resources>
    <resource type="irq" value="25" />
    <resource type="memory" value="c5110000-c5113fff" />
    <resource type="memory" value="c5100000-c510ffff" />
   </resources>
   <hints>
    <hint name="icon" value="disc" />
    <hint name="pci.class" value="0x108" />
    <hint name="pci.device" value="0x100" />
    <hint name="pci.subdevice" value="0x101" />
    <hint name="pci.subvendor" value="0x1BB1" />
    <hint name="pci.vendor" value="0x1BB1" />
   </hints>
  </node>
  <node id="nvme" claimed="true" class="storage" handle="PCI:0000:61:00.0" modalias="pci:v00008086d00000A54sv00008086sd00004802bc01sc08i02">
   <description>Non-Volatile memory controller</description>
   <product>NVMe Datacenter SSD [3DNAND, Beta Rock Controller]</product>
   <vendor>Intel Corporation</vendor>
   <physid>0</physid>
   <subsysproduct>Intel Corporation</subsysproduct>
   <subsysvendor>Intel Corporation</subsysvendor>
   <businfo>pci@0000:61:00.0</businfo>
   <version>00</version>
   <width units="bits">64</width>
   <clock units="Hz">33000000</clock>
   <configuration>
    <setting id="driver" value="nvme" />
    <setting id="latency" value="0" />
   </configuration>
   <capabilities>
    <capability id="nvme" />
    <capability id="pm" >Power Management</capability>
    <capability id="msix" >MSI-X</capability>
    <capability id="pciexpress" >PCI Express</capability>
    <capability id="msi" >Message Signalled Interrupts</capability>
    <capability id="nvm_express" />
    <capability id="bus_master" >bus mastering</capability>
    <capability id="cap_list" >PCI capabilities listing</capability>
    <capability id="rom" >extension ROM</capability>
   </capabilities>
   <resources>
    <resource type="irq" value="160" />
    <resource type="memory" value="c3010000-c3013fff" />
    <resource type="memory" value="c3000000-c300ffff" />
   </resources>
   <hints>
    <hint name="icon" value="disc" />
    <hint name="pci.class" value="0x108" />
    <hint name="pci.device" value="0xA54" />
    <hint name="pci.subdevice" value="0x4802" />
    <hint name="pci.subvendor" value="0x8086" />
    <hint name="pci.vendor" value="0x8086" />
   </hints>
  </node>
  <node id="nvme" claimed="true" class="storage" handle="PCI:0000:63:00.0" modalias="pci:v00001BB1d00000100sv00001BB1sd00000101bc01sc08i02">
   <description>Non-Volatile memory controller</description>
   <product>Nytro Flash Storage</product>
   <vendor>Seagate Technology PLC</vendor>
   <physid>0</physid>
   <subsysproduct>Seagate Technology PLC</subsysproduct>
   <subsysvendor>Seagate Technology PLC</subsysvendor>
   <businfo>pci@0000:63:00.0</businfo>
   <version>00</version>
   <width units="bits">64</width>
   <clock units="Hz">33000000</clock>
   <configuration>
    <setting id="driver" value="nvme" />
    <setting id="latency" value="0" />
   </configuration>
   <capabilities>
    <capability id="nvme" />
    <capability id="pm" >Power Management</capability>
    <capability id="pciexpress" >PCI Express</capability>
    <capability id="msix" >MSI-X</capability>
    <capability id="nvm_express" />
    <capability id="bus_master" >bus mastering</capability>
    <capability id="cap_list" >PCI capabilities listing</capability>
    <capability id="rom" >extension ROM</capability>
   </capabilities>
   <resources>
    <resource type="irq" value="25" />
    <resource type="memory" value="c5010000-c5013fff" />
    <resource type="memory" value="c5000000-c500ffff" />
   </resources>
   <hints>
    <hint name="icon" value="disc" />
    <hint name="pci.class" value="0x108" />
    <hint name="pci.device" value="0x100" />
    <hint name="pci.subdevice" value="0x101" />
    <hint name="pci.subvendor" value="0x1BB1" />
    <hint name="pci.vendor" value="0x1BB1" />
   </hints>
  </node>
</list>
